<?xml version="1.0" encoding="UTF-8"?>
<record_update table="wf_element_activity">
    <wf_element_activity action="INSERT_OR_UPDATE">
        <access>public</access>
        <attributes/>
        <base_provider display_value="Powershell">59155499eb512100b2f88a7af106feae</base_provider>
        <category/>
        <checked_out_by display_value="System Administrator">6816f79cc0a8016401c5a33be04be441</checked_out_by>
        <default_height/>
        <default_width/>
        <description/>
        <image>images/heisenberg_icons/workflow_ie8/provider_powershell.png</image>
        <input_meta>{"name":"Input","type":"DATA_OBJECT","properties":[{"name":"RequesterName","type":"STRING","mandatory":false}]}</input_meta>
        <input_process_script/>
        <input_transform>{"source":"172.31.12.48","script_type":"command","command":"set-content -path \"c:\\temp\\hw.txt\" -value \"hello world\"\nwrite-host \"hello world\"","midScriptFile":"","powershellVariables":"[{\"name\":\"\",\"type\":\"plain\",\"value\":\"\"}]","use_mid_service_account":"false","credential_tag":"AWS","midCapabilities":"427709a60a0006bc7d2904e99132532d"}</input_transform>
        <local_variables/>
        <name>helloworld</name>
        <output_meta>{"name":"Output","type":"DATA_OBJECT","properties":[{"name":"Output1","type":"STRING"}]}</output_meta>
        <output_process_script/>
        <output_transform/>
        <processing_script/>
        <sample_payloads>{}</sample_payloads>
        <short_description/>
        <style/>
        <sys_class_name>wf_element_activity</sys_class_name>
        <sys_created_by>admin</sys_created_by>
        <sys_created_on>2018-02-06 09:49:59</sys_created_on>
        <sys_id>ee69e72adb401300c0eaf11ebf961917</sys_id>
        <sys_mod_count>13</sys_mod_count>
        <sys_name>helloworld</sys_name>
        <sys_package display_value="NeedIt" source="x_58872_needit">6ead8e780f603200cd674f8ce1050ed1</sys_package>
        <sys_policy/>
        <sys_scope display_value="NeedIt">6ead8e780f603200cd674f8ce1050ed1</sys_scope>
        <sys_update_name>wf_element_activity_ee69e72adb401300c0eaf11ebf961917</sys_update_name>
        <sys_updated_by>admin</sys_updated_by>
        <sys_updated_on>2018-02-06 14:51:53</sys_updated_on>
        <version_container_id>8c892fe6db401300c0eaf11ebf96194c</version_container_id>
    </wf_element_activity>
    <sys_translated_text action="delete_multiple" query="documentkey=ee69e72adb401300c0eaf11ebf961917"/>
    <wf_versionable action="INSERT_OR_UPDATE">
        <checked_out>2018-02-06 09:49:59</checked_out>
        <checked_out_by display_value="System Administrator">6816f79cc0a8016401c5a33be04be441</checked_out_by>
        <published>false</published>
        <sys_created_by>admin</sys_created_by>
        <sys_created_on>2018-02-06 09:49:59</sys_created_on>
        <sys_id>44892fe6db401300c0eaf11ebf96194d</sys_id>
        <sys_mod_count>0</sys_mod_count>
        <sys_updated_by>admin</sys_updated_by>
        <sys_updated_on>2018-02-06 09:49:59</sys_updated_on>
        <valid_from/>
        <valid_to/>
        <version>1</version>
        <version_container_id>8c892fe6db401300c0eaf11ebf96194c</version_container_id>
        <wf_element_definition display_value="helloworld">ee69e72adb401300c0eaf11ebf961917</wf_element_definition>
    </wf_versionable>
</record_update>
